scout_apm/__init__.py
scout_apm/bottle.py
scout_apm/celery.py
scout_apm/compat.py
scout_apm/dramatiq.py
scout_apm/falcon.py
scout_apm/fastmcp.py
scout_apm/huey.py
scout_apm/hug.py
scout_apm/rq.py
scout_apm/sqlalchemy.py
scout_apm/api/__init__.py
scout_apm/async_/__init__.py
scout_apm/async_/api.py
scout_apm/async_/starlette.py
scout_apm/async_/instruments/__init__.py
scout_apm/async_/instruments/jinja2.py
scout_apm/core/__init__.py
scout_apm/core/backtrace.py
scout_apm/core/config.py
scout_apm/core/context.py
scout_apm/core/error.py
scout_apm/core/error_service.py
scout_apm/core/metadata.py
scout_apm/core/n_plus_one_tracker.py
scout_apm/core/objtrace.py
scout_apm/core/platform_detection.py
scout_apm/core/queue_time.py
scout_apm/core/sampler.py
scout_apm/core/stacktracer.py
scout_apm/core/threading.py
scout_apm/core/tracked_request.py
scout_apm/core/web_requests.py
scout_apm/core/agent/__init__.py
scout_apm/core/agent/commands.py
scout_apm/core/agent/manager.py
scout_apm/core/agent/socket.py
scout_apm/core/cli/__init__.py
scout_apm/core/cli/core_agent_manager.py
scout_apm/core/samplers/__init__.py
scout_apm/core/samplers/cpu.py
scout_apm/core/samplers/memory.py
scout_apm/core/samplers/thread.py
scout_apm/django/__init__.py
scout_apm/django/apps.py
scout_apm/django/middleware.py
scout_apm/django/request.py
scout_apm/django/instruments/__init__.py
scout_apm/django/instruments/huey.py
scout_apm/django/instruments/sql.py
scout_apm/django/instruments/template.py
scout_apm/flask/__init__.py
scout_apm/flask/sqlalchemy.py
scout_apm/instruments/__init__.py
scout_apm/instruments/elasticsearch.py
scout_apm/instruments/jinja2.py
scout_apm/instruments/pymongo.py
scout_apm/instruments/redis.py
scout_apm/instruments/urllib3.py
scout_apm-3.5.2.dist-info/licenses/LICENSE
scout_apm-3.5.2.dist-info/METADATA
scout_apm-3.5.2.dist-info/WHEEL
scout_apm-3.5.2.dist-info/entry_points.txt
scout_apm-3.5.2.dist-info/top_level.txt
scout_apm-3.5.2.dist-info/RECORD
