Metadata-Version: 2.4
Name: scout_apm
Version: 3.5.2
Summary: Scout Application Performance Monitoring Agent
Home-page: https://github.com/scoutapp/scout_apm_python
Author: Scout
Author-email: support@scoutapm.com
License: MIT
Project-URL: Documentation, https://docs.scoutapm.com/#python-agent
Project-URL: Changelog, https://github.com/scoutapp/scout_apm_python/blob/master/CHANGELOG.md
Keywords: apm,performance monitoring,development
Classifier: Development Status :: 5 - Production/Stable
Classifier: Framework :: Bottle
Classifier: Framework :: Django
Classifier: Framework :: Django :: 3.2
Classifier: Framework :: Django :: 4.0
Classifier: Framework :: Django :: 4.1
Classifier: Framework :: Django :: 4.2
Classifier: Framework :: Flask
Classifier: Intended Audience :: Developers
Classifier: Topic :: System :: Monitoring
Classifier: License :: OSI Approved :: MIT License
Classifier: Operating System :: MacOS
Classifier: Operating System :: POSIX
Classifier: Operating System :: POSIX :: Linux
Classifier: Programming Language :: Python :: 3.8
Classifier: Programming Language :: Python :: 3.9
Classifier: Programming Language :: Python :: 3.10
Classifier: Programming Language :: Python :: 3.11
Classifier: Programming Language :: Python :: 3.12
Requires-Python: >=3.8, <4
License-File: LICENSE
Requires-Dist: asgiref
Requires-Dist: psutil>=5
Requires-Dist: urllib3
Requires-Dist: certifi
Requires-Dist: wrapt<2.0,>=1.10
Dynamic: author
Dynamic: author-email
Dynamic: classifier
Dynamic: description
Dynamic: description-content-type
Dynamic: home-page
Dynamic: keywords
Dynamic: license
Dynamic: license-file
Dynamic: project-url
Dynamic: requires-dist
Dynamic: requires-python
Dynamic: summary
